{
  "type": "Feature",
  "stac_version": "2.2.0",
  "id": "ERA5_WIND_V",
  "properties": {
    "license": "",
    "Description": "",
    "providers": [
      {
        "name": "Sentinel Hub",
        "description": "",
        "url": "https://services.sentinel-hub.com"
      }
    ],
    "dataSource": "",
    "cube:dimensions": {
      "x": {
        "axis": "x",
        "extent": [
          -179.999755859375,
          179.99977453631897
        ],
        "type": "spatial"
      },
      "y": {
        "axis": "y",
        "extent": [
          -90.12489004526765,
          90.125
        ],
        "type": "spatial"
      },
      "time": {
        "extent": [
          "2019-01-01T00:00:00Z",
          "2022-04-01T00:00:00Z"
        ],
        "type": "temporal",
        "step": ""
      },
      "bands": {
        "name": "bands",
        "extent": [
          null,
          null
        ],
        "values": [
          "windv10m"
        ]
      }
    },
    "datetime": null,
    "raster:bands": [],
    "title": "Wind_10m_v",
    "datasource_type": "byoc-3043d07f-3c20-410c-9a87-7da720942ab8",
    "description": "Gridded ERA5 is the fifth generation ECMWF reanalysis for the global climate and weather for the past 4 to 7 decades. This parameter is the wind V field",
    "keywords": [
      "copernicus services",
      "C3S",
      "open data",
      "sentinel hub",
      "raster",
      "race challenges"
    ],
    "use_case_S4E": [],
    "use_case_WER": [],
    "use_case_NHM": [],
    "use_case_NILU": [],
    "platform": [
      "other"
    ]
  },
  "geometry": {
    "type": "Polygon",
    "coordinates": [
      [
        -179.999755859375,
        -90.12489004526765
      ],
      [
        -179.999755859375,
        90.125
      ],
      [
        179.99977453631897,
        90.125
      ],
      [
        179.99977453631897,
        -90.12489004526765
      ]
    ]
  },
  "links": [
    {
      "rel": "root",
      "href": "../catalog.json",
      "type": "application/json",
      "title": "data-access catalog"
    },
    {
      "rel": "parent",
      "href": "../catalog.json",
      "type": "application/json",
      "title": "data-access catalog"
    }
  ],
  "assets": {
    "thumbnail": {
      "href": "https://collections.eurodatacube.com/wind_10m_v/wind_10m_v.png",
      "roles": [
        "thumbnail"
      ]
    }
  },
  "bbox": [
    -179.999755859375,
    -90.12489004526765,
    179.99977453631897,
    90.125
  ],
  "stac_extensions": [
    "https://stac-extensions.github.io/raster/v1.1.0/schema.json",
    "https://stac-extensions.github.io/datacube/v2.0.0/schema.json"
  ]
}